CellDiffusion/__init__.py
CellDiffusion/_version.py
CellDiffusion/core.py
CellDiffusion/diffusion.py
CellDiffusion/models.py
CellDiffusion/utils.py
celldiff-0.1.0.dist-info/licenses/LICENSE
celldiff-0.1.0.dist-info/METADATA
celldiff-0.1.0.dist-info/WHEEL
celldiff-0.1.0.dist-info/top_level.txt
celldiff-0.1.0.dist-info/RECORD
