Metadata-Version: 2.4
Name: celldiff
Version: 0.1.0
Summary: A Python package for generating pseudo-cells using diffusion models
Home-page: https://github.com/ShiltonZhang/CellDiffusion
Author: Xiaochen Zhang
Author-email: xiaochen.zhang3@student.unimelb.edu.au
License: AGPL-3.0
Project-URL: Bug Reports, https://github.com/ShiltonZhang/CellDiffusion/issues
Project-URL: Source, https://github.com/ShiltonZhang/CellDiffusion
Keywords: single-cell,diffusion-models,pseudo-cells,bioinformatics,machine-learning
Classifier: Development Status :: 3 - Alpha
Classifier: Intended Audience :: Science/Research
Classifier: Topic :: Scientific/Engineering :: Bio-Informatics
Classifier: License :: OSI Approved :: GNU Affero General Public License v3
Classifier: Programming Language :: Python :: 3
Classifier: Programming Language :: Python :: 3.8
Classifier: Programming Language :: Python :: 3.9
Classifier: Programming Language :: Python :: 3.10
Classifier: Programming Language :: Python :: 3.11
Requires-Python: >=3.8
License-File: LICENSE
Requires-Dist: numpy>=1.21.0
Requires-Dist: pandas>=1.3.0
Requires-Dist: scanpy>=1.9.0
Requires-Dist: torch>=1.12.0
Requires-Dist: torchvision>=0.13.0
Requires-Dist: einops>=0.6.0
Requires-Dist: tqdm>=4.64.0
Requires-Dist: anndata>=0.8.0
Requires-Dist: scipy>=1.7.0
Requires-Dist: scikit-learn>=1.0.0
Requires-Dist: matplotlib>=3.5.0
Requires-Dist: seaborn>=0.11.0
Provides-Extra: dev
Requires-Dist: pytest>=6.0; extra == "dev"
Requires-Dist: pytest-cov; extra == "dev"
Requires-Dist: black; extra == "dev"
Requires-Dist: flake8; extra == "dev"
Requires-Dist: mypy; extra == "dev"
Requires-Dist: jupyter; extra == "dev"
Requires-Dist: matplotlib; extra == "dev"
Requires-Dist: seaborn; extra == "dev"
Provides-Extra: docs
Requires-Dist: sphinx; extra == "docs"
Requires-Dist: sphinx-rtd-theme; extra == "docs"
Requires-Dist: sphinxcontrib-napoleon; extra == "docs"
Dynamic: author
Dynamic: author-email
Dynamic: classifier
Dynamic: description
Dynamic: description-content-type
Dynamic: home-page
Dynamic: keywords
Dynamic: license
Dynamic: license-file
Dynamic: project-url
Dynamic: provides-extra
Dynamic: requires-dist
Dynamic: requires-python
Dynamic: summary
